Workbook

Sheet Dashboard
A1: TITAN COMPANY LIMITED — STOCK VALUATION DASHBOARD
A2: DCF + Relative Valuation Summary | Valuation date 27-Jul-2026
B4: INTRINSIC VALUE / SHARE | C4: CURRENT SHARE PRICE | D4: IMPLIED UPSIDE | E4: WACC | F4: TV % OF EV
B5: ='DCF Valuation'!C37 -> 784.87415 | C5: =Inputs!C11 -> 4698.2 | D5: ='DCF Valuation'!C39 -> -0.83294152 | E5: ='DCF Valuation'!C11 -> 0.12673137 | F5: ='DCF Valuation'!C33 -> 0.74699318
B6: vs current price (below) | C6: NSE, 27-Jul-2026 | D6: DCF base case | E6: CAPM-based | F6: Gordon growth
A8: VALUATION FOOTBALL FIELD
B9: Method | C9: Low (Rs) | D9: Value (Rs) | E9: High (Rs)
B10: Current Market Price | C10: =Inputs!C11 -> 4698.2 | D10: =Inputs!C11 -> 4698.2 | E10: =Inputs!C11 -> 4698.2
B11: DCF - Sensitivity Range | C11: =MIN('Sensitivity Analysis'!C8:G12) -> 628.55419 | D11: ='DCF Valuation'!C37 -> 784.87415 | E11: =MAX('Sensitivity Analysis'!C8:G12) -> 1050.384
B12: Comps - P/E Multiple | C12: ='Comparable Companies'!C15 -> 1072.2041 | D12: ='Comparable Companies'!C15 -> 1072.2041 | E12: ='Comparable Companies'!C15 -> 1072.2041
B13: Comps - EV/EBITDA Multiple | C13: ='Comparable Companies'!C22 -> 1153.5861 | D13: ='Comparable Companies'!C22 -> 1153.5861 | E13: ='Comparable Companies'!C22 -> 1153.5861
B15: Football-field chart (right) plots the Value column for each method against the current market price, with the DCF row also showing its full sensitivity range as error bars via Low/High.
A17: READING THIS VALUATION
B18: Titan trades at roughly a 90x trailing P/E (Rs 4,698 price vs ~Rs 52 TTM EPS) - far above both the DCF intrinsic value and the peer-comps range shown below. That gap is not a modelling error: the market is pricing in a multi-decade compounding growth story (India's organised-jewellery penetration is still low, and Titan is the category leader with pricing power, brand trust, and store-network runway) that a 5-year explicit DCF horizon and a 5% terminal growth rate cannot capture. Treat this the way an equity research desk would treat question 'Your DCF says -80%, do you trust it?' - stress-test a much longer explicit high-growth period, a higher terminal growth rate, or a terminal EV/EBITDA exit multiple instead of Gordon Growth, and compare the result to what the current price implies (a reverse-DCF exercise) before drawing any conclusion about over- or under-valuation.
A20: 5-YEAR REVENUE TREND: HISTORICAL + FORECAST
B21: Year | C21: FY21 | D21: FY22 | E21: FY23 | F21: FY24 | G21: FY25 | H21: FY26E | I21: FY27E | J21: FY28E | K21: FY29E | L21: FY30E
B22: Revenue (Rs Cr) | C22: ='Historical Financials'!C5 -> 20088 | D22: ='Historical Financials'!D5 -> 27000 | E22: ='Historical Financials'!E5 -> 36150 | F22: ='Historical Financials'!F5 -> 46751 | G22: ='Historical Financials'!G5 -> 57143 | H22: =Forecast!C6 -> 65714.45 | I22: =Forecast!D6 -> 74914.473 | J22: =Forecast!E6 -> 84653.354 | K22: =Forecast!F6 -> 94811.757 | L22: =Forecast!G6 -> 105241.05
B24: All KPI cards and charts are live formulas referencing the Inputs, Historical, Forecast, DCF, Comps, and Sensitivity sheets - change any blue input cell anywhere in the workbook and this dashboard recalculates end to end.
B46: Charts are embedded directly in this Dashboard sheet (Football Field on the left, Revenue Trend on the right) so they travel with the workbook - no separate chart sheet to lose track of.

Sheet Inputs
A1: STOCK VALUATION MODEL — INPUTS & ASSUMPTIONS
A2: Titan Company Limited (NSE: TITAN | BSE: 500114) | DCF + Relative Valuation | All figures in Rs Crore unless stated
A4: 1. COMPANY SNAPSHOT
B6: Company Name | C6: Titan Company Limited
B7: Ticker | C7: NSE: TITAN | BSE: 500114
B8: Sector / Industry | C8: Consumer Discretionary - Jewellery, Watches & Eyewear
B9: Valuation Date | C9: 27-Jul-2026
B10: Reporting Currency | C10: INR Crore (Rs Cr) - per-share figures in Rs
B11: Current Share Price (Rs) | C11: 4698.2
B12: Shares Outstanding (Cr) | C12: 88.7
B13: Market Capitalisation (Rs Cr) | C13: =C11*C12 -> 416730.34
B15: Source: NSE closing price via Google Finance / Kotak Neo, 27-Jul-2026 (Rs 4,698.20; market cap Rs 4,15,218 Cr). Shares outstanding implied from market cap divided by price (Kotak Neo / Business Standard, Jul-2026).
A17: 2. FORECAST DRIVER ASSUMPTIONS (FY26E-FY30E)
B18: Driver | C18: FY26E | D18: FY27E | E18: FY28E | F18: FY29E | G18: FY30E
B19: Revenue Growth % | C19: 0.15 | D19: 0.14 | E19: 0.13 | F19: 0.12 | G19: 0.11
B20: EBIT Margin % | C20: 0.105 | D20: 0.108 | E20: 0.11 | F20: 0.112 | G20: 0.113
B21: D&A (% of Revenue) | C21: 0.015 | D21: 0.015 | E21: 0.015 | F21: 0.015 | G21: 0.015
B22: Capex (% of Revenue) | C22: 0.012 | D22: 0.012 | E22: 0.012 | F22: 0.012 | G22: 0.012
B23: Incr. NWC (% of Delta Revenue) | C23: 0.2 | D23: 0.2 | E23: 0.2 | F23: 0.2 | G23: 0.2
B24: Effective Tax Rate % | C24: 0.25 | H24: One flat rate applied across all forecast years
B26: Revenue growth tapers from a still-strong 15.0% toward an 11.0% long-run rate as the jewellery/watches franchise matures; EBIT margin normalises modestly toward Titan's historical 11%-11.5% range. NWC is a much larger share of incremental revenue than a services business (20%) because gold jewellery inventory is capital-intensive. These are illustrative forecasting assumptions for this exercise, not company guidance or analyst consensus - flex them and watch the DCF output move.
A28: 3. WACC - COST OF CAPITAL (CAPM)
B29: Risk-Free Rate (10Y India G-Sec) | C29: 0.069
B30: Beta (5Y regression vs NIFTY 50) | C30: 0.9
B31: Equity Risk Premium (India) | C31: 0.065
B32: Cost of Equity (Ke) = Rf + Beta x ERP | C32: =C29+C30*C31 -> 0.1275
B33: Pre-tax Cost of Debt (Kd) | C33: 0.08
B34: After-tax Cost of Debt = Kd x (1-t) | C34: =C33*(1-C24) -> 0.06
B36: Beta of 0.90 reflects Titan's consumer-discretionary, premium-valuation profile - higher than an export-linked IT services business. Kd approximates the cost of gold-metal-loan and lease financing Titan uses to fund jewellery inventory, since the company carries modest net debt (unlike an asset-light IT major).
A38: 4. TERMINAL VALUE ASSUMPTION
B39: Terminal Growth Rate (g) | C39: 0.05
B40: Set at/below long-run nominal India GDP growth, consistent with the Gordon Growth assumption that no firm outgrows the economy forever.
A42: COLOUR LEGEND
B43: Blue text | C43: Hardcoded input - UNLOCKED, safe to edit to flex the model
B44: Black text | C44: Formula - LOCKED, protected from accidental edits
B45: Green text | C45: Link pulling a value from another sheet - LOCKED
B46: This workbook is sheet-protected (no password) so formulas can't be broken by accident. Only blue cells are unlocked. In Excel: Review > Unprotect Sheet to make further structural changes.

Sheet Historical Financials
A1: HISTORICAL FINANCIALS — FY21-FY25 (Rs Crore, Consolidated)
A2: Titan Company Limited | Consolidated results
B4: Rs Crore unless noted | C4: FY21 | D4: FY22 | E4: FY23 | F4: FY24 | G4: FY25
B5: Revenue | C5: 20088 | D5: 27000 | E5: 36150 | F5: 46751 | G5: 57143
B6: Revenue Growth % | C6: n.a. | D6: =D5/C5-1 -> 0.34408602 | E6: =E5/D5-1 -> 0.33888889 | F6: =F5/E5-1 -> 0.29325035 | G6: =G5/F5-1 -> 0.22228402
B7: EBIT Margin % (operating margin) | C7: 0.1225 | D7: 0.115 | E7: 0.114 | F7: 0.1132 | G7: 0.0996
B8: EBIT | C8: =C5*C7 -> 2460.78 | D8: =D5*D7 -> 3105 | E8: =E5*E7 -> 4121.1 | F8: =F5*F7 -> 5292.2132 | G8: =G5*G7 -> 5691.4428
B9: Net Income (reported) | C9: 973 | D9: 2153 | E9: 2802 | F9: 3496 | G9: 3337
B10: Net Margin % | C10: =C9/C5 -> 0.048436878 | D10: =D9/D5 -> 0.079740741 | E10: =E9/E5 -> 0.077510373 | F10: =F9/F5 -> 0.074779149 | G10: =G9/G5 -> 0.058397354
B11: D&A | C11: 300 | D11: 400 | E11: 540 | F11: 700 | G11: 860
B12: EBITDA | C12: =C8+C11 -> 2760.78 | D12: =D8+D11 -> 3505 | E12: =E8+E11 -> 4661.1 | F12: =F8+F11 -> 5992.2132 | G12: =G8+G11 -> 6551.4428
B13: Capex | C13: 200 | D13: 270 | E13: 360 | F13: 470 | G13: 570
B14: Increase in NWC | C14: 1500 | D14: 2200 | E14: 2800 | F14: 3200 | G14: 3100
B15: Total Debt (gold metal loans + leases) | C15: 2500 | D15: 3000 | E15: 3600 | F15: 4200 | G15: 4800
B16: Cash & Investments | C16: 1200 | D16: 1400 | E16: 1700 | F16: 2000 | G16: 2300
B17: Net Debt / (Net Cash) | C17: =C15-C16 -> 1300 | D17: =D15-D16 -> 1600 | E17: =E15-E16 -> 1900 | F17: =F15-F16 -> 2200 | G17: =G15-G16 -> 2500
B18: Shares Outstanding (Cr) | C18: 87.9 | D18: 88.1 | E18: 88.3 | F18: 88.5 | G18: 88.7
B19: EPS (Rs) | C19: =C9/C18 -> 11.069397 | D19: =D9/D18 -> 24.438138 | E19: =E9/E18 -> 31.732729 | F19: =F9/F18 -> 39.502825 | G19: =G9/G18 -> 37.621195
A21: DATA SOURCES & NOTES
B22: Revenue and Net Income for FY21, FY24 and FY25 are Titan's reported consolidated Sales and Net Profit (Business Standard capital-market reports of Titan's board-approved results, and Screener.in consolidated financials, accessed Jul-2026): FY21 Rs 20,088 Cr / Rs 973 Cr; FY24 Rs 46,751 Cr / Rs 3,496 Cr; FY25 Rs 57,143 Cr / Rs 3,337 Cr (FY25 profit dipped versus FY24 due to the customs-duty cut on gold compressing margins, as flagged in Titan's own results commentary).
B23: FY22 and FY23 Revenue/Net Income are approximated from the company's known post-pandemic recovery trajectory between the confirmed FY21 and FY24 anchors - treat as directional, not exact, and replace with the audited FY22/FY23 Annual Report figures for a production-grade model.
B24: EBIT Margin (operating margin): FY21 and FY24/FY25 approximate Titan's reported OPM (~12.25% FY21 standalone proxy, 11.32% FY24, 9.96% FY25 per Business Standard capital-market commentary); FY22/FY23 are smoothed/interpolated between these anchors.
B25: D&A, Capex, Increase in NWC, Total Debt, Cash & Investments: not individually itemised in the summary press releases used for this project - estimated at typical proportions for a jewellery/watches retailer (inventory-heavy NWC, moderate lease and gold-metal-loan debt). Replace with exact cash-flow-statement and balance-sheet figures from the Titan Annual Report for a production-grade model.

Sheet Forecast
A1: 5-YEAR DRIVER-BASED FORECAST — FY26E-FY30E (Rs Crore)
A2: Titan Company Limited | Revenue and margins driven by Inputs sheet assumptions
B4: Rs Crore unless noted | C4: FY26E | D4: FY27E | E4: FY28E | F4: FY29E | G4: FY30E
B5: Revenue Growth % (from Inputs) | C5: =Inputs!C19 -> 0.15 | D5: =Inputs!D19 -> 0.14 | E5: =Inputs!E19 -> 0.13 | F5: =Inputs!F19 -> 0.12 | G5: =Inputs!G19 -> 0.11
B6: Revenue | C6: ='Historical Financials'!G5*(1+C5) -> 65714.45 | D6: =C6*(1+D5) -> 74914.473 | E6: =D6*(1+E5) -> 84653.354 | F6: =E6*(1+F5) -> 94811.757 | G6: =F6*(1+G5) -> 105241.05
B7: EBIT Margin % (from Inputs) | C7: =Inputs!C20 -> 0.105 | D7: =Inputs!D20 -> 0.108 | E7: =Inputs!E20 -> 0.11 | F7: =Inputs!F20 -> 0.112 | G7: =Inputs!G20 -> 0.113
B8: EBIT | C8: =C6*C7 -> 6900.0172 | D8: =D6*D7 -> 8090.7631 | E8: =E6*E7 -> 9311.869 | F8: =F6*F7 -> 10618.917 | G8: =G6*G7 -> 11892.239
B9: Tax Rate % (from Inputs) | C9: =Inputs!$C$24 -> 0.25 | D9: =Inputs!$C$24 -> 0.25 | E9: =Inputs!$C$24 -> 0.25 | F9: =Inputs!$C$24 -> 0.25 | G9: =Inputs!$C$24 -> 0.25
B10: NOPAT = EBIT x (1-tax) | C10: =C8*(1-C9) -> 5175.0129 | D10: =D8*(1-D9) -> 6068.0723 | E10: =E8*(1-E9) -> 6983.9017 | F10: =F8*(1-F9) -> 7964.1876 | G10: =G8*(1-G9) -> 8919.179
B11: (+) D&A | C11: =C6*Inputs!C21 -> 985.71675 | D11: =D6*Inputs!D21 -> 1123.7171 | E11: =E6*Inputs!E21 -> 1269.8003 | F11: =F6*Inputs!F21 -> 1422.1764 | G11: =G6*Inputs!G21 -> 1578.6158
B12: (-) Capex | C12: =C6*Inputs!C22 -> 788.5734 | D12: =D6*Inputs!D22 -> 898.97368 | E12: =E6*Inputs!E22 -> 1015.8403 | F12: =F6*Inputs!F22 -> 1137.7411 | G12: =G6*Inputs!G22 -> 1262.8926
B13: (-) Increase in NWC | C13: =(C6-'Historical Financials'!G5)*Inputs!C23 -> 1714.29 | D13: =(D6-C6)*Inputs!D23 -> 1840.0046 | E13: =(E6-D6)*Inputs!E23 -> 1947.7763 | F13: =(F6-E6)*Inputs!F23 -> 2031.6805 | G13: =(G6-F6)*Inputs!G23 -> 2085.8587
B14: FREE CASH FLOW TO FIRM (FCFF) | C14: =C10+C11-C12-C13 -> 3657.8663 | D14: =D10+D11-D12-D13 -> 4452.8111 | E14: =E10+E11-E12-E13 -> 5290.0855 | F14: =F10+F11-F12-F13 -> 6216.9424 | G14: =G10+G11-G12-G13 -> 7149.0435
B16: FCFF = NOPAT + D&A - Capex - Increase in NWC. Every driver traces back to the Inputs sheet, so changing a single blue assumption cell reflows the entire forecast, DCF, and Sensitivity output.

Sheet DCF Valuation
A1: DCF VALUATION — ENTERPRISE VALUE TO INTRINSIC VALUE PER SHARE
A2: Titan Company Limited | Discounted Cash Flow (FCFF), WACC via CAPM, Gordon Growth terminal value
A4: 1. WACC BUILD-UP (MARKET-VALUE WEIGHTS)
B5: Market Value of Equity (Rs Cr) | C5: =Inputs!C13 -> 416730.34
B6: Market Value of Debt (Rs Cr, FY25 total debt) | C6: ='Historical Financials'!G15 -> 4800
B7: Weight of Equity We = E/(D+E) | C7: =C5/(C5+C6) -> 0.98861292
B8: Weight of Debt Wd = D/(D+E) | C8: =C6/(C5+C6) -> 0.011387081
B9: Cost of Equity (Ke) | C9: =Inputs!C32 -> 0.1275
B10: After-tax Cost of Debt (Kd) | C10: =Inputs!C34 -> 0.06
B11: WACC = We x Ke + Wd x Kd(1-t) | C11: =C7*C9+C8*C10 -> 0.12673137
B13: Unlike an asset-light IT major, Titan carries meaningful working-capital debt (gold metal loans) to fund jewellery inventory, so its debt weight - while still small next to its market capitalisation - is non-trivial and modestly pulls WACC below the pure cost of equity.
A15: 2. FREE CASH FLOW DISCOUNTING
B16: Rs Crore unless noted | C16: FY26E | D16: FY27E | E16: FY28E | F16: FY29E | G16: FY30E
B17: Forecast Year n | C17: 1 | D17: 2 | E17: 3 | F17: 4 | G17: 5
B18: FCFF (from Forecast sheet) | C18: =Forecast!C14 -> 3657.8663 | D18: =Forecast!D14 -> 4452.8111 | E18: =Forecast!E14 -> 5290.0855 | F18: =Forecast!F14 -> 6216.9424 | G18: =Forecast!G14 -> 7149.0435
B19: Discount Factor = 1/(1+WACC)^n | C19: =1/(1+$C$11)^C17 -> 0.88752299 | D19: =1/(1+$C$11)^D17 -> 0.78769706 | E19: =1/(1+$C$11)^E17 -> 0.69909926 | F19: =1/(1+$C$11)^F17 -> 0.62046666 | G19: =1/(1+$C$11)^G17 -> 0.55067843
B20: PV of FCFF | C20: =C18*C19 -> 3246.4404 | D20: =D18*D19 -> 3507.4663 | E20: =E18*E19 -> 3698.2948 | F20: =F18*F19 -> 3857.4055 | G20: =G18*G19 -> 3936.8241
B22: Sum of PV of Explicit FCFF (Yr 1-5) | C22: =SUM(C20:G20) -> 18246.431
A24: 3. TERMINAL VALUE (GORDON GROWTH)
B25: Final-Year FCFF (FY30E) | C25: =G18 -> 7149.0435
B26: Terminal Growth Rate (g) | C26: =Inputs!C39 -> 0.05
B27: Terminal Value = FCFF x (1+g) / (WACC-g) | C27: =C25*(1+C26)/(C11-C26) -> 97828.248
B28: Discount Factor (Year 5) | C28: =G19 -> 0.55067843
B29: PV of Terminal Value | C29: =C27*C28 -> 53871.906
A31: 4. ENTERPRISE VALUE TO INTRINSIC VALUE PER SHARE
B32: Enterprise Value = Sum PV(FCFF) + PV(TV) | C32: =C22+C29 -> 72118.337
B33: TV as % of Enterprise Value | C33: =C29/C32 -> 0.74699318
B34: (-) Net Debt / (+) Net Cash (FY25) | C34: ='Historical Financials'!G17 -> 2500
B35: Equity Value = EV - Net Debt | C35: =C32-C34 -> 69618.337
B36: Shares Outstanding (Cr) | C36: =Inputs!C12 -> 88.7
B37: INTRINSIC VALUE PER SHARE (Rs) | C37: =C35/C36 -> 784.87415
B38: Current Share Price (Rs) | C38: =Inputs!C11 -> 4698.2
B39: IMPLIED UPSIDE / (DOWNSIDE) % | C39: =C37/C38-1 -> -0.83294152
B41: Cross-check: TV should typically fall in a 60-80% band of Enterprise Value for a mature, moderate-growth company - if it is far outside that range, revisit the growth/margin taper or the WACC-g spread. For a structural-growth consumer story like Titan, also compare against the 'Reading This Valuation' note on the Dashboard before concluding the stock is mispriced.

Sheet Comparable Companies
A1: RELATIVE VALUATION — PEER P/E & EV/EBITDA COMPS
A2: Indian organised-jewellery retail peer set | Trailing multiples, Jul-2026
B4: Company | C4: P/E (TTM) | D4: EV/EBITDA
B5: Kalyan Jewellers | C5: 35 | D5: 18
B6: Senco Gold | C6: 22 | D6: 14
B7: Thangamayil Jewellery | C7: 45 | D7: 28
B8: PC Jeweller | C8: 12 | D8: 8
B9: Median (peer set) | C9: =MEDIAN(C5:C8) -> 28.5 | D9: =MEDIAN(D5:D8) -> 16
B11: P/E and EV/EBITDA are approximate trailing multiples compiled from public market-data sites (TipRanks, MarketScreener, ValueResearch, Upstox) in Jul-2026; treat as illustrative comps rather than a precise, single-day snapshot. Refresh from Screener.in or stockanalysis.com before relying on this for a live decision.
A13: APPLY TO TITAN COMPANY LIMITED
B14: FY25 EPS (Rs) | C14: ='Historical Financials'!G19 -> 37.621195
B15: Implied Value / Share via P/E | C15: =C14*C9 -> 1072.2041
B17: FY25 EBITDA (Rs Cr) | C17: ='Historical Financials'!G12 -> 6551.4428
B18: Implied EV via EV/EBITDA | C18: =C17*D9 -> 104823.08
B19: (-) Net Debt / (+) Net Cash (FY25) | C19: ='Historical Financials'!G17 -> 2500
B20: Implied Equity Value | C20: =C18-C19 -> 102323.08
B21: Shares Outstanding (Cr) | C21: =Inputs!C12 -> 88.7
B22: Implied Value / Share via EV/EBITDA | C22: =C20/C21 -> 1153.5861
B24: Average Relative-Valuation Estimate | C24: =AVERAGE(C15,C22) -> 1112.8951
B26: Cross-check the DCF against these comps: a DCF far outside the peer-implied range signals an assumption (usually WACC or terminal growth) worth revisiting, not necessarily a mispriced stock.

Sheet Sensitivity Analysis
A1: TWO-WAY SENSITIVITY — WACC x TERMINAL GROWTH (Rs / Share)
A2: Titan Company Limited | Intrinsic value per share across a WACC and terminal-growth grid, fully formula-driven
B4: Base WACC | C4: ='DCF Valuation'!C11 -> 0.12673137
B5: Base Terminal Growth (g) | C5: ='DCF Valuation'!C26 -> 0.05
B7: Value / Share (Rs) | C7: =$C$5+-0.01 -> 0.04 | D7: =$C$5+-0.005 -> 0.045 | E7: =$C$5+0 -> 0.05 | F7: =$C$5+0.005 -> 0.055 | G7: =$C$5+0.01 -> 0.06
B8: =$C$4+-0.01 -> 0.11673137 | C8: =('DCF Valuation'!C$18/(1+$B$8)^1+'DCF Valuation'!D$18/(1+$B$8)^2+'DCF Valuation'!E$18/(1+$B$8)^3+'DCF Valuation'!F$18/(1+$B$8)^4+'DCF Valuation'!G$18/(1+$B$8)^5+('DCF Valuation'!G$18*(1+C$7)/($B$8-C$7))/(1+$B$8)^5-'DCF Valuation'!$C$34)/'DCF Valuation'!$C$36 -> 812.2819 | D8: =('DCF Valuation'!C$18/(1+$B$8)^1+'DCF Valuation'!D$18/(1+$B$8)^2+'DCF Valuation'!E$18/(1+$B$8)^3+'DCF Valuation'!F$18/(1+$B$8)^4+'DCF Valuation'!G$18/(1+$B$8)^5+('DCF Valuation'!G$18*(1+D$7)/($B$8-D$7))/(1+$B$8)^5-'DCF Valuation'!$C$34)/'DCF Valuation'!$C$36 -> 859.35983 | E8: =('DCF Valuation'!C$18/(1+$B$8)^1+'DCF Valuation'!D$18/(1+$B$8)^2+'DCF Valuation'!E$18/(1+$B$8)^3+'DCF Valuation'!F$18/(1+$B$8)^4+'DCF Valuation'!G$18/(1+$B$8)^5+('DCF Valuation'!G$18*(1+E$7)/($B$8-E$7))/(1+$B$8)^5-'DCF Valuation'!$C$34)/'DCF Valuation'!$C$36 -> 913.4926 | F8: =('DCF Valuation'!C$18/(1+$B$8)^1+'DCF Valuation'!D$18/(1+$B$8)^2+'DCF Valuation'!E$18/(1+$B$8)^3+'DCF Valuation'!F$18/(1+$B$8)^4+'DCF Valuation'!G$18/(1+$B$8)^5+('DCF Valuation'!G$18*(1+F$7)/($B$8-F$7))/(1+$B$8)^5-'DCF Valuation'!$C$34)/'DCF Valuation'!$C$36 -> 976.39446 | G8: =('DCF Valuation'!C$18/(1+$B$8)^1+'DCF Valuation'!D$18/(1+$B$8)^2+'DCF Valuation'!E$18/(1+$B$8)^3+'DCF Valuation'!F$18/(1+$B$8)^4+'DCF Valuation'!G$18/(1+$B$8)^5+('DCF Valuation'!G$18*(1+G$7)/($B$8-G$7))/(1+$B$8)^5-'DCF Valuation'!$C$34)/'DCF Valuation'!$C$36 -> 1050.384
B9: =$C$4+-0.005 -> 0.12173137 | C9: =('DCF Valuation'!C$18/(1+$B$9)^1+'DCF Valuation'!D$18/(1+$B$9)^2+'DCF Valuation'!E$18/(1+$B$9)^3+'DCF Valuation'!F$18/(1+$B$9)^4+'DCF Valuation'!G$18/(1+$B$9)^5+('DCF Valuation'!G$18*(1+C$7)/($B$9-C$7))/(1+$B$9)^5-'DCF Valuation'!$C$34)/'DCF Valuation'!$C$36 -> 757.84318 | D9: =('DCF Valuation'!C$18/(1+$B$9)^1+'DCF Valuation'!D$18/(1+$B$9)^2+'DCF Valuation'!E$18/(1+$B$9)^3+'DCF Valuation'!F$18/(1+$B$9)^4+'DCF Valuation'!G$18/(1+$B$9)^5+('DCF Valuation'!G$18*(1+D$7)/($B$9-D$7))/(1+$B$9)^5-'DCF Valuation'!$C$34)/'DCF Valuation'!$C$36 -> 798.42926 | E9: =('DCF Valuation'!C$18/(1+$B$9)^1+'DCF Valuation'!D$18/(1+$B$9)^2+'DCF Valuation'!E$18/(1+$B$9)^3+'DCF Valuation'!F$18/(1+$B$9)^4+'DCF Valuation'!G$18/(1+$B$9)^5+('DCF Valuation'!G$18*(1+E$7)/($B$9-E$7))/(1+$B$9)^5-'DCF Valuation'!$C$34)/'DCF Valuation'!$C$36 -> 844.6734 | F9: =('DCF Valuation'!C$18/(1+$B$9)^1+'DCF Valuation'!D$18/(1+$B$9)^2+'DCF Valuation'!E$18/(1+$B$9)^3+'DCF Valuation'!F$18/(1+$B$9)^4+'DCF Valuation'!G$18/(1+$B$9)^5+('DCF Valuation'!G$18*(1+F$7)/($B$9-F$7))/(1+$B$9)^5-'DCF Valuation'!$C$34)/'DCF Valuation'!$C$36 -> 897.84745 | G9: =('DCF Valuation'!C$18/(1+$B$9)^1+'DCF Valuation'!D$18/(1+$B$9)^2+'DCF Valuation'!E$18/(1+$B$9)^3+'DCF Valuation'!F$18/(1+$B$9)^4+'DCF Valuation'!G$18/(1+$B$9)^5+('DCF Valuation'!G$18*(1+G$7)/($B$9-G$7))/(1+$B$9)^5-'DCF Valuation'!$C$34)/'DCF Valuation'!$C$36 -> 959.63527
B10: =$C$4+0 -> 0.12673137 | C10: =('DCF Valuation'!C$18/(1+$B$10)^1+'DCF Valuation'!D$18/(1+$B$10)^2+'DCF Valuation'!E$18/(1+$B$10)^3+'DCF Valuation'!F$18/(1+$B$10)^4+'DCF Valuation'!G$18/(1+$B$10)^5+('DCF Valuation'!G$18*(1+C$7)/($B$10-C$7))/(1+$B$10)^5-'DCF Valuation'!$C$34)/'DCF Valuation'!$C$36 -> 709.73027 | D10: =('DCF Valuation'!C$18/(1+$B$10)^1+'DCF Valuation'!D$18/(1+$B$10)^2+'DCF Valuation'!E$18/(1+$B$10)^3+'DCF Valuation'!F$18/(1+$B$10)^4+'DCF Valuation'!G$18/(1+$B$10)^5+('DCF Valuation'!G$18*(1+D$7)/($B$10-D$7))/(1+$B$10)^5-'DCF Valuation'!$C$34)/'DCF Valuation'!$C$36 -> 745.00371 | E10: =('DCF Valuation'!C$18/(1+$B$10)^1+'DCF Valuation'!D$18/(1+$B$10)^2+'DCF Valuation'!E$18/(1+$B$10)^3+'DCF Valuation'!F$18/(1+$B$10)^4+'DCF Valuation'!G$18/(1+$B$10)^5+('DCF Valuation'!G$18*(1+E$7)/($B$10-E$7))/(1+$B$10)^5-'DCF Valuation'!$C$34)/'DCF Valuation'!$C$36 -> 784.87415 | F10: =('DCF Valuation'!C$18/(1+$B$10)^1+'DCF Valuation'!D$18/(1+$B$10)^2+'DCF Valuation'!E$18/(1+$B$10)^3+'DCF Valuation'!F$18/(1+$B$10)^4+'DCF Valuation'!G$18/(1+$B$10)^5+('DCF Valuation'!G$18*(1+F$7)/($B$10-F$7))/(1+$B$10)^5-'DCF Valuation'!$C$34)/'DCF Valuation'!$C$36 -> 830.30289 | G10: =('DCF Valuation'!C$18/(1+$B$10)^1+'DCF Valuation'!D$18/(1+$B$10)^2+'DCF Valuation'!E$18/(1+$B$10)^3+'DCF Valuation'!F$18/(1+$B$10)^4+'DCF Valuation'!G$18/(1+$B$10)^5+('DCF Valuation'!G$18*(1+G$7)/($B$10-G$7))/(1+$B$10)^5-'DCF Valuation'!$C$34)/'DCF Valuation'!$C$36 -> 882.53933
B11: =$C$4+0.005 -> 0.13173137 | C11: =('DCF Valuation'!C$18/(1+$B$11)^1+'DCF Valuation'!D$18/(1+$B$11)^2+'DCF Valuation'!E$18/(1+$B$11)^3+'DCF Valuation'!F$18/(1+$B$11)^4+'DCF Valuation'!G$18/(1+$B$11)^5+('DCF Valuation'!G$18*(1+C$7)/($B$11-C$7))/(1+$B$11)^5-'DCF Valuation'!$C$34)/'DCF Valuation'!$C$36 -> 666.90772 | D11: =('DCF Valuation'!C$18/(1+$B$11)^1+'DCF Valuation'!D$18/(1+$B$11)^2+'DCF Valuation'!E$18/(1+$B$11)^3+'DCF Valuation'!F$18/(1+$B$11)^4+'DCF Valuation'!G$18/(1+$B$11)^5+('DCF Valuation'!G$18*(1+D$7)/($B$11-D$7))/(1+$B$11)^5-'DCF Valuation'!$C$34)/'DCF Valuation'!$C$36 -> 697.78413 | E11: =('DCF Valuation'!C$18/(1+$B$11)^1+'DCF Valuation'!D$18/(1+$B$11)^2+'DCF Valuation'!E$18/(1+$B$11)^3+'DCF Valuation'!F$18/(1+$B$11)^4+'DCF Valuation'!G$18/(1+$B$11)^5+('DCF Valuation'!G$18*(1+E$7)/($B$11-E$7))/(1+$B$11)^5-'DCF Valuation'!$C$34)/'DCF Valuation'!$C$36 -> 732.43834 | F11: =('DCF Valuation'!C$18/(1+$B$11)^1+'DCF Valuation'!D$18/(1+$B$11)^2+'DCF Valuation'!E$18/(1+$B$11)^3+'DCF Valuation'!F$18/(1+$B$11)^4+'DCF Valuation'!G$18/(1+$B$11)^5+('DCF Valuation'!G$18*(1+F$7)/($B$11-F$7))/(1+$B$11)^5-'DCF Valuation'!$C$34)/'DCF Valuation'!$C$36 -> 771.60884 | G11: =('DCF Valuation'!C$18/(1+$B$11)^1+'DCF Valuation'!D$18/(1+$B$11)^2+'DCF Valuation'!E$18/(1+$B$11)^3+'DCF Valuation'!F$18/(1+$B$11)^4+'DCF Valuation'!G$18/(1+$B$11)^5+('DCF Valuation'!G$18*(1+G$7)/($B$11-G$7))/(1+$B$11)^5-'DCF Valuation'!$C$34)/'DCF Valuation'!$C$36 -> 816.24006
B12: =$C$4+0.01 -> 0.13673137 | C12: =('DCF Valuation'!C$18/(1+$B$12)^1+'DCF Valuation'!D$18/(1+$B$12)^2+'DCF Valuation'!E$18/(1+$B$12)^3+'DCF Valuation'!F$18/(1+$B$12)^4+'DCF Valuation'!G$18/(1+$B$12)^5+('DCF Valuation'!G$18*(1+C$7)/($B$12-C$7))/(1+$B$12)^5-'DCF Valuation'!$C$34)/'DCF Valuation'!$C$36 -> 628.55419 | D12: =('DCF Valuation'!C$18/(1+$B$12)^1+'DCF Valuation'!D$18/(1+$B$12)^2+'DCF Valuation'!E$18/(1+$B$12)^3+'DCF Valuation'!F$18/(1+$B$12)^4+'DCF Valuation'!G$18/(1+$B$12)^5+('DCF Valuation'!G$18*(1+D$7)/($B$12-D$7))/(1+$B$12)^5-'DCF Valuation'!$C$34)/'DCF Valuation'!$C$36 -> 655.75474 | E12: =('DCF Valuation'!C$18/(1+$B$12)^1+'DCF Valuation'!D$18/(1+$B$12)^2+'DCF Valuation'!E$18/(1+$B$12)^3+'DCF Valuation'!F$18/(1+$B$12)^4+'DCF Valuation'!G$18/(1+$B$12)^5+('DCF Valuation'!G$18*(1+E$7)/($B$12-E$7))/(1+$B$12)^5-'DCF Valuation'!$C$34)/'DCF Valuation'!$C$36 -> 686.09147 | F12: =('DCF Valuation'!C$18/(1+$B$12)^1+'DCF Valuation'!D$18/(1+$B$12)^2+'DCF Valuation'!E$18/(1+$B$12)^3+'DCF Valuation'!F$18/(1+$B$12)^4+'DCF Valuation'!G$18/(1+$B$12)^5+('DCF Valuation'!G$18*(1+F$7)/($B$12-F$7))/(1+$B$12)^5-'DCF Valuation'!$C$34)/'DCF Valuation'!$C$36 -> 720.13997 | G12: =('DCF Valuation'!C$18/(1+$B$12)^1+'DCF Valuation'!D$18/(1+$B$12)^2+'DCF Valuation'!E$18/(1+$B$12)^3+'DCF Valuation'!F$18/(1+$B$12)^4+'DCF Valuation'!G$18/(1+$B$12)^5+('DCF Valuation'!G$18*(1+G$7)/($B$12-G$7))/(1+$B$12)^5-'DCF Valuation'!$C$34)/'DCF Valuation'!$C$36 -> 758.62583
B14: Rows = WACC (base +/- 1.0%/0.5%); Columns = terminal growth g (base +/- 1.0%/0.5%). Each cell independently recomputes PV(FCFF) + PV(Terminal Value), less net debt, over shares outstanding - so the whole grid updates automatically if any Inputs-sheet assumption changes. The highlighted centre cell reproduces the DCF Valuation sheet's headline intrinsic value per share.
B15: Row label = WACC (%) | Column header = Terminal growth g (%)
